{
  "ticker": "AAPL",
  "model_type": "LSTM",
  "horizon": 3,
  "feature_key": "F1",
  "feature_cols": [
    "Close"
  ],
  "n_features": 1,
  "study_name": "LSTM_H3_F1",
  "optuna_best_trial": {
    "trial_number": 158,
    "values": [
      0.031286278170977184,
      0.9582892060279846
    ],
    "params": {
      "units": 128,
      "lstm_layers": 4,
      "dropout": 0.2,
      "optimizer": "adamW",
      "learning_rate": 0.002655402589812554
    }
  },
  "test_level": {
    "rmse": 4.205807209014893,
    "r2": 0.9820470809936523
  },
  "artifacts": {
    "checkpoint": "..\\data\\best_models\\AAPL\\LSTM_H3_F1_AAPL.pt",
    "config": "..\\data\\best_models\\AAPL\\LSTM_H3_F1_AAPL.config.json",
    "metrics": "..\\data\\best_models\\AAPL\\LSTM_H3_F1_AAPL.metrics.json",
    "history": "..\\data\\best_models\\AAPL\\LSTM_H3_F1_AAPL.history.json",
    "plot_pdf": "..\\data\\Figures\\Plots\\AAPL\\LSTM_H3_F1_AAPL.pdf",
    "plot_png": "..\\data\\Figures\\Plots\\AAPL\\LSTM_H3_F1_AAPL.png",
    "table_csv": "..\\data\\Figures\\Tables\\AAPL\\LSTM_H3_F1_AAPL.csv",
    "table_tex": "..\\data\\Figures\\Tables\\AAPL\\LSTM_H3_F1_AAPL.tex"
  }
}